LICENSE
MANIFEST.in
README.md
requirements.txt
setup.py
s_rna_tools/__init__.py
s_rna_tools/__main__.py
s_rna_tools/countifier.py
s_rna_tools/create_unique.py
s_rna_tools/find_match.py
s_rna_tools/group_sequences.py
s_rna_tools/join_duplicates.py
s_rna_tools/match_all_smrna.py
s_rna_tools/rna_blast.py
s_rna_tools/utils.py
s_rna_tools.egg-info/PKG-INFO
s_rna_tools.egg-info/SOURCES.txt
s_rna_tools.egg-info/dependency_links.txt
s_rna_tools.egg-info/entry_points.txt
s_rna_tools.egg-info/not-zip-safe
s_rna_tools.egg-info/requires.txt
s_rna_tools.egg-info/top_level.txt