Metadata-Version: 2.1
Name: s-rna-tools
Version: 0.0.3
Summary: Tools for handling Small RNA sequences.
Home-page: https://github.com/luissian/s-rna-tools
Author: Luis Chapado
Author-email: chapado.l@gmail.com
License: GNU GENERAL PUBLIC LICENSE v.3
Keywords: RNA,bioinformatics,pipeline,sequencing,NGS,next generation sequencing
License-File: LICENSE
